[
    {
        "device_id": "8955e82234d53d61",
        "key": "key12345",
        "expirydate": "31-12-2025",
        "Allowoffline": true
    },
    {
        "device_id": "2feae36d525b4c36",
        "key": "d/OOQlx7BAk",
        "expirydate": "01-09-2026",
        "Allowoffline": true
    },
    {
        "device_id": "c440b933fbeba476",
        "key": "xI4/TENl6w",
        "expirydate": "01-09-2026",
        "Allowoffline": true
    }, 
    {
        "device_id": "6490cec255af1441",
        "key": "Cqp3SIG78io",
        "expirydate": "01-09-2026",
        "Allowoffline": true
    }, 
    {
        "device_id": "a3a0a239fa49e91e",
        "key": "x47cv29b",
        "expirydate": "01-09-2026",
        "Allowoffline": true
    }, 
    {
        "device_id": "25d57163d71ad499",
        "key": "fhj37jf8p",
        "expirydate": "01-09-2026",
        "Allowoffline": true
    }, 
    {
        "device_id": "e8aa5b16dfd316ab",
        "key": "hdh89jf1",
        "expirydate": "01-09-2026",
        "Allowoffline": true
    }, 
    {
        "device_id": "41eda369d9dfb8ed",
        "key": "hfjk8381",
        "expirydate": "01-09-2026",
        "Allowoffline": true
    }, 
]
